ligo_requests-0.0.1-py3.8-nspkg.pth
ligo/requests/__init__.py
ligo/requests/_version.py
ligo/requests/auth.py
ligo/requests/cert_reload.py
ligo/requests/errors.py
ligo/requests/file.py
ligo/requests/user_agent.py
ligo/requests/tests/__init__.py
ligo/requests/tests/conftest.py
ligo/requests/tests/test_auth.py
ligo/requests/tests/test_cert_reload.py
ligo/requests/tests/test_errors.py
ligo/requests/tests/test_file.py
ligo/requests/tests/test_user_agent.py
ligo_requests-0.0.1.dist-info/LICENSE.rst
ligo_requests-0.0.1.dist-info/METADATA
ligo_requests-0.0.1.dist-info/WHEEL
ligo_requests-0.0.1.dist-info/namespace_packages.txt
ligo_requests-0.0.1.dist-info/top_level.txt
ligo_requests-0.0.1.dist-info/RECORD
